LICENSE.txt
MANIFEST.in
README.rst
setup.cfg
setup.py
lambda_controller/__init__.py
lambda_controller/shell.py
lambda_controller.egg-info/PKG-INFO
lambda_controller.egg-info/SOURCES.txt
lambda_controller.egg-info/dependency_links.txt
lambda_controller.egg-info/entry_points.txt
lambda_controller.egg-info/requires.txt
lambda_controller.egg-info/top_level.txt