Metadata-Version: 1.1
Name: lambda-controller
Version: 0.0.2
Summary: lambda-controller project
Home-page: UNKNOWN
Author: cloudfish7
Author-email: tskwdev@gmail.com
License: MIT
Keywords: aws lambda lambda-controller
Platform: UNKNOWN
Classifier: Development Status :: 3 - Alpha
Classifier: Intended Audience :: Developers
Classifier: Topic :: Software Development :: Build Tools
Classifier: License :: OSI Approved :: MIT License
Classifier: Programming Language :: Python :: 2.7
Classifier: Programming Language :: Python :: 3
Classifier: Programming Language :: Python :: 3.2
Classifier: Programming Language :: Python :: 3.3
Classifier: Programming Language :: Python :: 3.4
Classifier: Programming Language :: Python :: 3.5
